MaxFlowAeiu.cpython-38-darwin.so
MaxFlowAeiu/MaxFlowAeiu.cpython-38-darwin.so
MaxFlowAeiu-0.1.4.dist-info/LICENCE.txt
MaxFlowAeiu-0.1.4.dist-info/METADATA
MaxFlowAeiu-0.1.4.dist-info/WHEEL
MaxFlowAeiu-0.1.4.dist-info/top_level.txt
MaxFlowAeiu-0.1.4.dist-info/RECORD
