Metadata-Version: 2.1
Name: MaxFlowAeiu
Version: 0.1.4
Summary: Execution of the Fork Fulkerson method to find the maximum flow of a network
Home-page: https://github.com/optimizacion-2-2022-gh-classroom/practica-2-segunda-parte-EddOselotl
Author: Team-2
Author-email: 
License: MIT
Keywords: max flow
Classifier: License :: OSI Approved :: MIT License
Classifier: Programming Language :: Python :: 3
Classifier: Intended Audience :: Education
Requires-Python: >=3.8
License-File: LICENCE.txt
Requires-Dist: numpy (>=1.21.5)
